lcps/__init__.py
lcps/__init__.pyc
lcps/_astropy_init.py
lcps/_astropy_init.pyc
lcps/conftest.py
lcps/lcps_batch.py
lcps/lcps_io.py
lcps/slidingWindow.py
lcps/slidingWindow.pyc
lcps/version.py
lcps/version.pyc
lcps-0.1.dev12.dist-info/DESCRIPTION.rst
lcps-0.1.dev12.dist-info/METADATA
lcps-0.1.dev12.dist-info/RECORD
lcps-0.1.dev12.dist-info/WHEEL
lcps-0.1.dev12.dist-info/entry_points.txt
lcps-0.1.dev12.dist-info/metadata.json
lcps-0.1.dev12.dist-info/top_level.txt
