Metadata-Version: 2.0
Name: lcps
Version: 0.1.dev12
Summary: Light Curve Pre-Selection
Home-page: http://astropy.org/
Author: Martin Schlecker
Author-email: martin.schlecker@tum.de
License: BSD
Platform: UNKNOWN
Requires-Dist: astropy
